etl2osm/__init__.py
etl2osm/api.py
etl2osm/cli.py
etl2osm/extract.py
etl2osm/load.py
etl2osm/models.py
etl2osm/transform.py
etl2osm-0.2.0.dist-info/DESCRIPTION.rst
etl2osm-0.2.0.dist-info/METADATA
etl2osm-0.2.0.dist-info/RECORD
etl2osm-0.2.0.dist-info/WHEEL
etl2osm-0.2.0.dist-info/entry_points.txt
etl2osm-0.2.0.dist-info/metadata.json
etl2osm-0.2.0.dist-info/top_level.txt
