Metadata-Version: 2.0
Name: etl2osm
Version: 0.2.0
Summary: Extract, Transform and Load to OpenStreetMap.
Home-page: https://github.com/osmottawa/etl2osm/
Author: OSM Canada Team
Author-email: carriere.denis@gmail.com
License: The MIT License
Download-URL: https://github.com/osmottawa/etl2osm/
Keywords: etl extract transform load shapefile geojson osm
Platform: UNKNOWN
Classifier: Development Status :: 5 - Production/Stable
Classifier: Intended Audience :: Developers
Classifier: Intended Audience :: Science/Research
Classifier: License :: OSI Approved :: Apache Software License
Classifier: Natural Language :: English
Classifier: Operating System :: OS Independent
Classifier: Programming Language :: Python :: 2.6
Classifier: Programming Language :: Python :: 2.7
Classifier: Programming Language :: Python :: 3
Classifier: Programming Language :: Python :: 3.1
Classifier: Programming Language :: Python :: 3.3
Classifier: Programming Language :: Python :: 3.4
Classifier: Topic :: Internet
Classifier: Topic :: Internet :: WWW/HTTP
Classifier: Topic :: Scientific/Engineering :: GIS
Classifier: Topic :: Software Development :: Libraries :: Python Modules
Requires-Dist: click (==5.1)
Requires-Dist: fiona
Requires-Dist: lxml
Requires-Dist: pyyaml
Requires-Dist: six (==1.10.0)
